simplewebserver/__init__.py
simplewebserver/decorator.py
simplewebserver/handler.py
simplewebserver/server.py
simplewebserver/utils.py
simplewebserver-0.0.6.dist-info/LICENSE
simplewebserver-0.0.6.dist-info/METADATA
simplewebserver-0.0.6.dist-info/WHEEL
simplewebserver-0.0.6.dist-info/top_level.txt
simplewebserver-0.0.6.dist-info/RECORD
