Metadata-Version: 2.1
Name: simplewebserver
Version: 0.0.6
Summary: A simple http.server based web server
Home-page: https://github.com/kejun91/simple-web-server
Author: Jun Ke
Author-email: kejun91@gmail.com
Classifier: Programming Language :: Python :: 3
Classifier: License :: OSI Approved :: MIT License
Classifier: Operating System :: OS Independent
Requires-Python: >=3.6
License-File: LICENSE
